{
  "item": [
    {
      "name": "Portfolio Generation",
      "description": "Generate professional developer portfolios from GitHub profiles",
      "item": [
        {
          "id": "315d35ba-acf8-491d-8db4-9d4bf06d3800",
          "name": "Generate developer portfolio",
          "request": {
            "name": "Generate developer portfolio",
            "description": {
              "content": "Scans a GitHub user's public repositories and generates a professional portfolio with AI",
              "type": "text/plain"
            },
            "url": {
              "path": [
                "api",
                "v1",
                "portfolio",
                "generate"
              ],
              "host": [
                "{{baseUrl}}"
              ],
              "query": [],
              "variable": []
            },
            "header": [
              {
                "key": "Content-Type",
                "value": "application/json"
              },
              {
                "key": "Accept",
                "value": "*/*"
              }
            ],
            "method": "POST",
            "body": {
              "mode": "raw",
              "raw": "{\n  \"githubUsername\": \"<string>\"\n}",
              "options": {
                "raw": {
                  "headerFamily": "json",
                  "language": "json"
                }
              }
            },
            "auth": null
          },
          "response": [
            {
              "id": "2cc2f5b6-102a-473a-802f-cae4efc7cfb8",
              "name": "Portfolio generated successfully",
              "originalRequest": {
                "url": {
                  "path": [
                    "api",
                    "v1",
                    "portfolio",
                    "generate"
                  ],
                  "host": [
                    "{{baseUrl}}"
                  ],
                  "query": [],
                  "variable": []
                },
                "header": [
                  {
                    "key": "Content-Type",
                    "value": "application/json"
                  },
                  {
                    "key": "Accept",
                    "value": "*/*"
                  }
                ],
                "method": "POST",
                "body": {
                  "mode": "raw",
                  "raw": "{\n  \"githubUsername\": \"<string>\"\n}",
                  "options": {
                    "raw": {
                      "headerFamily": "json",
                      "language": "json"
                    }
                  }
                }
              },
              "status": "OK",
              "code": 200,
              "header": [
                {
                  "key": "Content-Type",
                  "value": "*/*"
                }
              ],
              "body": "{\n  \"id\": \"<long>\",\n  \"githubUsername\": \"<string>\",\n  \"developerName\": \"<string>\",\n  \"professionalSummary\": \"<string>\",\n  \"topSkills\": [\n    \"<string>\",\n    \"<string>\"\n  ],\n  \"selectedProjects\": [\n    {\n      \"repoName\": \"<string>\",\n      \"repoUrl\": \"<string>\",\n      \"description\": \"<string>\",\n      \"techStack\": [\n        \"<string>\",\n        \"<string>\"\n      ],\n      \"whyNotable\": \"<string>\",\n      \"category\": \"<string>\"\n    },\n    {\n      \"repoName\": \"<string>\",\n      \"repoUrl\": \"<string>\",\n      \"description\": \"<string>\",\n      \"techStack\": [\n        \"<string>\",\n        \"<string>\"\n      ],\n      \"whyNotable\": \"<string>\",\n      \"category\": \"<string>\"\n    }\n  ],\n  \"skillsByCategory\": {\n    \"key_0\": [\n      \"<string>\",\n      \"<string>\"\n    ],\n    \"key_1\": [\n      \"<string>\",\n      \"<string>\"\n    ],\n    \"key_2\": [\n      \"<string>\",\n      \"<string>\"\n    ]\n  },\n  \"profileHighlights\": [\n    \"<string>\",\n    \"<string>\"\n  ],\n  \"totalPublicRepos\": \"<integer>\",\n  \"createdAt\": \"<dateTime>\"\n}",
              "cookie": [],
              "_postman_previewlanguage": "text"
            },
            {
              "id": "d7f5a497-6a0c-4182-93cf-9db52e01c73e",
              "name": "Invalid GitHub username",
              "originalRequest": {
                "url": {
                  "path": [
                    "api",
                    "v1",
                    "portfolio",
                    "generate"
                  ],
                  "host": [
                    "{{baseUrl}}"
                  ],
                  "query": [],
                  "variable": []
                },
                "header": [
                  {
                    "key": "Content-Type",
                    "value": "application/json"
                  },
                  {
                    "key": "Accept",
                    "value": "*/*"
                  }
                ],
                "method": "POST",
                "body": {
                  "mode": "raw",
                  "raw": "{\n  \"githubUsername\": \"<string>\"\n}",
                  "options": {
                    "raw": {
                      "headerFamily": "json",
                      "language": "json"
                    }
                  }
                }
              },
              "status": "Bad Request",
              "code": 400,
              "header": [
                {
                  "key": "Content-Type",
                  "value": "*/*"
                }
              ],
              "body": "{\n  \"id\": \"<long>\",\n  \"githubUsername\": \"<string>\",\n  \"developerName\": \"<string>\",\n  \"professionalSummary\": \"<string>\",\n  \"topSkills\": [\n    \"<string>\",\n    \"<string>\"\n  ],\n  \"selectedProjects\": [\n    {\n      \"repoName\": \"<string>\",\n      \"repoUrl\": \"<string>\",\n      \"description\": \"<string>\",\n      \"techStack\": [\n        \"<string>\",\n        \"<string>\"\n      ],\n      \"whyNotable\": \"<string>\",\n      \"category\": \"<string>\"\n    },\n    {\n      \"repoName\": \"<string>\",\n      \"repoUrl\": \"<string>\",\n      \"description\": \"<string>\",\n      \"techStack\": [\n        \"<string>\",\n        \"<string>\"\n      ],\n      \"whyNotable\": \"<string>\",\n      \"category\": \"<string>\"\n    }\n  ],\n  \"skillsByCategory\": {\n    \"key_0\": [\n      \"<string>\",\n      \"<string>\"\n    ],\n    \"key_1\": [\n      \"<string>\",\n      \"<string>\"\n    ],\n    \"key_2\": [\n      \"<string>\",\n      \"<string>\"\n    ]\n  },\n  \"profileHighlights\": [\n    \"<string>\",\n    \"<string>\"\n  ],\n  \"totalPublicRepos\": \"<integer>\",\n  \"createdAt\": \"<dateTime>\"\n}",
              "cookie": [],
              "_postman_previewlanguage": "text"
            },
            {
              "id": "e3742c5c-b8a1-4597-a263-4d7813c8856a",
              "name": "GitHub user not found",
              "originalRequest": {
                "url": {
                  "path": [
                    "api",
                    "v1",
                    "portfolio",
                    "generate"
                  ],
                  "host": [
                    "{{baseUrl}}"
                  ],
                  "query": [],
                  "variable": []
                },
                "header": [
                  {
                    "key": "Content-Type",
                    "value": "application/json"
                  },
                  {
                    "key": "Accept",
                    "value": "*/*"
                  }
                ],
                "method": "POST",
                "body": {
                  "mode": "raw",
                  "raw": "{\n  \"githubUsername\": \"<string>\"\n}",
                  "options": {
                    "raw": {
                      "headerFamily": "json",
                      "language": "json"
                    }
                  }
                }
              },
              "status": "Not Found",
              "code": 404,
              "header": [
                {
                  "key": "Content-Type",
                  "value": "*/*"
                }
              ],
              "body": "{\n  \"id\": \"<long>\",\n  \"githubUsername\": \"<string>\",\n  \"developerName\": \"<string>\",\n  \"professionalSummary\": \"<string>\",\n  \"topSkills\": [\n    \"<string>\",\n    \"<string>\"\n  ],\n  \"selectedProjects\": [\n    {\n      \"repoName\": \"<string>\",\n      \"repoUrl\": \"<string>\",\n      \"description\": \"<string>\",\n      \"techStack\": [\n        \"<string>\",\n        \"<string>\"\n      ],\n      \"whyNotable\": \"<string>\",\n      \"category\": \"<string>\"\n    },\n    {\n      \"repoName\": \"<string>\",\n      \"repoUrl\": \"<string>\",\n      \"description\": \"<string>\",\n      \"techStack\": [\n        \"<string>\",\n        \"<string>\"\n      ],\n      \"whyNotable\": \"<string>\",\n      \"category\": \"<string>\"\n    }\n  ],\n  \"skillsByCategory\": {\n    \"key_0\": [\n      \"<string>\",\n      \"<string>\"\n    ],\n    \"key_1\": [\n      \"<string>\",\n      \"<string>\"\n    ],\n    \"key_2\": [\n      \"<string>\",\n      \"<string>\"\n    ]\n  },\n  \"profileHighlights\": [\n    \"<string>\",\n    \"<string>\"\n  ],\n  \"totalPublicRepos\": \"<integer>\",\n  \"createdAt\": \"<dateTime>\"\n}",
              "cookie": [],
              "_postman_previewlanguage": "text"
            }
          ],
          "event": [],
          "protocolProfileBehavior": {
            "disableBodyPruning": true
          }
        },
        {
          "id": "4affdeae-58c2-42b8-9054-52e2f6a0c1a2",
          "name": "List all portfolios",
          "request": {
            "name": "List all portfolios",
            "description": {
              "content": "Returns summary of all generated portfolios",
              "type": "text/plain"
            },
            "url": {
              "path": [
                "api",
                "v1",
                "portfolio"
              ],
              "host": [
                "{{baseUrl}}"
              ],
              "query": [],
              "variable": []
            },
            "header": [
              {
                "key": "Accept",
                "value": "*/*"
              }
            ],
            "method": "GET",
            "body": {},
            "auth": null
          },
          "response": [
            {
              "id": "d1ca8ca3-9323-4cd1-8aca-5edf30220088",
              "name": "OK",
              "originalRequest": {
                "url": {
                  "path": [
                    "api",
                    "v1",
                    "portfolio"
                  ],
                  "host": [
                    "{{baseUrl}}"
                  ],
                  "query": [],
                  "variable": []
                },
                "header": [
                  {
                    "key": "Accept",
                    "value": "*/*"
                  }
                ],
                "method": "GET",
                "body": {}
              },
              "status": "OK",
              "code": 200,
              "header": [
                {
                  "key": "Content-Type",
                  "value": "*/*"
                }
              ],
              "body": "[\n  {\n    \"id\": \"<long>\",\n    \"githubUsername\": \"<string>\",\n    \"developerName\": \"<string>\",\n    \"professionalSummary\": \"<string>\",\n    \"topSkills\": [\n      \"<string>\",\n      \"<string>\"\n    ],\n    \"totalPublicRepos\": \"<integer>\",\n    \"projectCount\": \"<integer>\",\n    \"createdAt\": \"<dateTime>\"\n  },\n  {\n    \"id\": \"<long>\",\n    \"githubUsername\": \"<string>\",\n    \"developerName\": \"<string>\",\n    \"professionalSummary\": \"<string>\",\n    \"topSkills\": [\n      \"<string>\",\n      \"<string>\"\n    ],\n    \"totalPublicRepos\": \"<integer>\",\n    \"projectCount\": \"<integer>\",\n    \"createdAt\": \"<dateTime>\"\n  }\n]",
              "cookie": [],
              "_postman_previewlanguage": "text"
            }
          ],
          "event": [],
          "protocolProfileBehavior": {
            "disableBodyPruning": true
          }
        },
        {
          "id": "562c5fa5-d500-4e15-83a5-1286cbbdd546",
          "name": "Get portfolio by ID",
          "request": {
            "name": "Get portfolio by ID",
            "description": {},
            "url": {
              "path": [
                "api",
                "v1",
                "portfolio",
                ":id"
              ],
              "host": [
                "{{baseUrl}}"
              ],
              "query": [],
              "variable": [
                {
                  "type": "any",
                  "value": "<long>",
                  "key": "id",
                  "disabled": false,
                  "description": {
                    "content": "(Required) ",
                    "type": "text/plain"
                  }
                }
              ]
            },
            "header": [
              {
                "key": "Accept",
                "value": "*/*"
              }
            ],
            "method": "GET",
            "body": {},
            "auth": null
          },
          "response": [
            {
              "id": "9245fb21-0808-4845-9baf-048f6309add1",
              "name": "Portfolio found",
              "originalRequest": {
                "url": {
                  "path": [
                    "api",
                    "v1",
                    "portfolio",
                    ":id"
                  ],
                  "host": [
                    "{{baseUrl}}"
                  ],
                  "query": [],
                  "variable": [
                    {
                      "disabled": false,
                      "description": {
                        "content": "(Required) ",
                        "type": "text/plain"
                      },
                      "type": "any",
                      "value": "<long>",
                      "key": "id"
                    }
                  ]
                },
                "header": [
                  {
                    "key": "Accept",
                    "value": "*/*"
                  }
                ],
                "method": "GET",
                "body": {}
              },
              "status": "OK",
              "code": 200,
              "header": [
                {
                  "key": "Content-Type",
                  "value": "*/*"
                }
              ],
              "body": "{\n  \"id\": \"<long>\",\n  \"githubUsername\": \"<string>\",\n  \"developerName\": \"<string>\",\n  \"professionalSummary\": \"<string>\",\n  \"topSkills\": [\n    \"<string>\",\n    \"<string>\"\n  ],\n  \"selectedProjects\": [\n    {\n      \"repoName\": \"<string>\",\n      \"repoUrl\": \"<string>\",\n      \"description\": \"<string>\",\n      \"techStack\": [\n        \"<string>\",\n        \"<string>\"\n      ],\n      \"whyNotable\": \"<string>\",\n      \"category\": \"<string>\"\n    },\n    {\n      \"repoName\": \"<string>\",\n      \"repoUrl\": \"<string>\",\n      \"description\": \"<string>\",\n      \"techStack\": [\n        \"<string>\",\n        \"<string>\"\n      ],\n      \"whyNotable\": \"<string>\",\n      \"category\": \"<string>\"\n    }\n  ],\n  \"skillsByCategory\": {\n    \"key_0\": [\n      \"<string>\",\n      \"<string>\"\n    ],\n    \"key_1\": [\n      \"<string>\",\n      \"<string>\"\n    ],\n    \"key_2\": [\n      \"<string>\",\n      \"<string>\"\n    ]\n  },\n  \"profileHighlights\": [\n    \"<string>\",\n    \"<string>\"\n  ],\n  \"totalPublicRepos\": \"<integer>\",\n  \"createdAt\": \"<dateTime>\"\n}",
              "cookie": [],
              "_postman_previewlanguage": "text"
            },
            {
              "id": "877b955f-80bc-41e0-8c73-9d05a985c7dd",
              "name": "Portfolio not found",
              "originalRequest": {
                "url": {
                  "path": [
                    "api",
                    "v1",
                    "portfolio",
                    ":id"
                  ],
                  "host": [
                    "{{baseUrl}}"
                  ],
                  "query": [],
                  "variable": [
                    {
                      "disabled": false,
                      "description": {
                        "content": "(Required) ",
                        "type": "text/plain"
                      },
                      "type": "any",
                      "value": "<long>",
                      "key": "id"
                    }
                  ]
                },
                "header": [
                  {
                    "key": "Accept",
                    "value": "*/*"
                  }
                ],
                "method": "GET",
                "body": {}
              },
              "status": "Not Found",
              "code": 404,
              "header": [
                {
                  "key": "Content-Type",
                  "value": "*/*"
                }
              ],
              "body": "{\n  \"id\": \"<long>\",\n  \"githubUsername\": \"<string>\",\n  \"developerName\": \"<string>\",\n  \"professionalSummary\": \"<string>\",\n  \"topSkills\": [\n    \"<string>\",\n    \"<string>\"\n  ],\n  \"selectedProjects\": [\n    {\n      \"repoName\": \"<string>\",\n      \"repoUrl\": \"<string>\",\n      \"description\": \"<string>\",\n      \"techStack\": [\n        \"<string>\",\n        \"<string>\"\n      ],\n      \"whyNotable\": \"<string>\",\n      \"category\": \"<string>\"\n    },\n    {\n      \"repoName\": \"<string>\",\n      \"repoUrl\": \"<string>\",\n      \"description\": \"<string>\",\n      \"techStack\": [\n        \"<string>\",\n        \"<string>\"\n      ],\n      \"whyNotable\": \"<string>\",\n      \"category\": \"<string>\"\n    }\n  ],\n  \"skillsByCategory\": {\n    \"key_0\": [\n      \"<string>\",\n      \"<string>\"\n    ],\n    \"key_1\": [\n      \"<string>\",\n      \"<string>\"\n    ],\n    \"key_2\": [\n      \"<string>\",\n      \"<string>\"\n    ]\n  },\n  \"profileHighlights\": [\n    \"<string>\",\n    \"<string>\"\n  ],\n  \"totalPublicRepos\": \"<integer>\",\n  \"createdAt\": \"<dateTime>\"\n}",
              "cookie": [],
              "_postman_previewlanguage": "text"
            }
          ],
          "event": [],
          "protocolProfileBehavior": {
            "disableBodyPruning": true
          }
        }
      ]
    },
    {
      "name": "Repository Analysis",
      "description": "Analyze GitHub repositories and generate READMEs",
      "item": [
        {
          "id": "a1188e5a-1237-43bc-b86d-d8f9a2702517",
          "name": "Commit README to repository",
          "request": {
            "name": "Commit README to repository",
            "description": {
              "content": "Commits a generated README directly to the user's GitHub repository. Requires OAuth authentication.",
              "type": "text/plain"
            },
            "url": {
              "path": [
                "api",
                "v1",
                "repos",
                "readme",
                "commit"
              ],
              "host": [
                "{{baseUrl}}"
              ],
              "query": [],
              "variable": []
            },
            "header": [
              {
                "key": "Content-Type",
                "value": "application/json"
              },
              {
                "key": "Accept",
                "value": "*/*"
              }
            ],
            "method": "POST",
            "body": {
              "mode": "raw",
              "raw": "{\n  \"readmeContent\": \"<string>\",\n  \"repoUrl\": \"https://github.com/pRBOac/a.git\"\n}",
              "options": {
                "raw": {
                  "headerFamily": "json",
                  "language": "json"
                }
              }
            },
            "auth": null
          },
          "response": [
            {
              "id": "c332683b-d1c7-4817-b4d4-cc2ecb6bd9a9",
              "name": "README committed successfully",
              "originalRequest": {
                "url": {
                  "path": [
                    "api",
                    "v1",
                    "repos",
                    "readme",
                    "commit"
                  ],
                  "host": [
                    "{{baseUrl}}"
                  ],
                  "query": [],
                  "variable": []
                },
                "header": [
                  {
                    "key": "Content-Type",
                    "value": "application/json"
                  },
                  {
                    "key": "Accept",
                    "value": "*/*"
                  }
                ],
                "method": "POST",
                "body": {
                  "mode": "raw",
                  "raw": "{\n  \"readmeContent\": \"<string>\",\n  \"repoUrl\": \"https://github.com/pRBOac/a.git\"\n}",
                  "options": {
                    "raw": {
                      "headerFamily": "json",
                      "language": "json"
                    }
                  }
                }
              },
              "status": "OK",
              "code": 200,
              "header": [
                {
                  "key": "Content-Type",
                  "value": "*/*"
                }
              ],
              "body": "{\n  \"commitSha\": \"<string>\",\n  \"commitUrl\": \"<string>\"\n}",
              "cookie": [],
              "_postman_previewlanguage": "text"
            },
            {
              "id": "32d02d83-1fa5-4c88-a468-ef39965a8f5b",
              "name": "OAuth authentication required",
              "originalRequest": {
                "url": {
                  "path": [
                    "api",
                    "v1",
                    "repos",
                    "readme",
                    "commit"
                  ],
                  "host": [
                    "{{baseUrl}}"
                  ],
                  "query": [],
                  "variable": []
                },
                "header": [
                  {
                    "key": "Content-Type",
                    "value": "application/json"
                  },
                  {
                    "key": "Accept",
                    "value": "*/*"
                  }
                ],
                "method": "POST",
                "body": {
                  "mode": "raw",
                  "raw": "{\n  \"readmeContent\": \"<string>\",\n  \"repoUrl\": \"https://github.com/pRBOac/a.git\"\n}",
                  "options": {
                    "raw": {
                      "headerFamily": "json",
                      "language": "json"
                    }
                  }
                }
              },
              "status": "Unauthorized",
              "code": 401,
              "header": [
                {
                  "key": "Content-Type",
                  "value": "*/*"
                }
              ],
              "body": "{\n  \"commitSha\": \"<string>\",\n  \"commitUrl\": \"<string>\"\n}",
              "cookie": [],
              "_postman_previewlanguage": "text"
            },
            {
              "id": "686c3e34-1716-4e9c-b44d-ce3ff16cd2f6",
              "name": "GitHub API error during commit",
              "originalRequest": {
                "url": {
                  "path": [
                    "api",
                    "v1",
                    "repos",
                    "readme",
                    "commit"
                  ],
                  "host": [
                    "{{baseUrl}}"
                  ],
                  "query": [],
                  "variable": []
                },
                "header": [
                  {
                    "key": "Content-Type",
                    "value": "application/json"
                  },
                  {
                    "key": "Accept",
                    "value": "*/*"
                  }
                ],
                "method": "POST",
                "body": {
                  "mode": "raw",
                  "raw": "{\n  \"readmeContent\": \"<string>\",\n  \"repoUrl\": \"https://github.com/pRBOac/a.git\"\n}",
                  "options": {
                    "raw": {
                      "headerFamily": "json",
                      "language": "json"
                    }
                  }
                }
              },
              "status": "Bad Gateway",
              "code": 502,
              "header": [
                {
                  "key": "Content-Type",
                  "value": "*/*"
                }
              ],
              "body": "{\n  \"commitSha\": \"<string>\",\n  \"commitUrl\": \"<string>\"\n}",
              "cookie": [],
              "_postman_previewlanguage": "text"
            }
          ],
          "event": [],
          "protocolProfileBehavior": {
            "disableBodyPruning": true
          }
        },
        {
          "id": "a9836e3d-7059-4fd7-a111-8a3dbd5fb3fa",
          "name": "Analyze a GitHub repository",
          "request": {
            "name": "Analyze a GitHub repository",
            "description": {
              "content": "Reads a GitHub repo, analyzes the code with AI, and generates a professional README",
              "type": "text/plain"
            },
            "url": {
              "path": [
                "api",
                "v1",
                "repos",
                "analyze"
              ],
              "host": [
                "{{baseUrl}}"
              ],
              "query": [],
              "variable": []
            },
            "header": [
              {
                "key": "Content-Type",
                "value": "application/json"
              },
              {
                "key": "Accept",
                "value": "*/*"
              }
            ],
            "method": "POST",
            "body": {
              "mode": "raw",
              "raw": "{\n  \"repoUrl\": \"https://github.com/UMSDqA/WtH9LVk9W.git\"\n}",
              "options": {
                "raw": {
                  "headerFamily": "json",
                  "language": "json"
                }
              }
            },
            "auth": null
          },
          "response": [
            {
              "id": "45965fd0-1610-49ee-bf34-1803b91a5091",
              "name": "Analysis completed successfully",
              "originalRequest": {
                "url": {
                  "path": [
                    "api",
                    "v1",
                    "repos",
                    "analyze"
                  ],
                  "host": [
                    "{{baseUrl}}"
                  ],
                  "query": [],
                  "variable": []
                },
                "header": [
                  {
                    "key": "Content-Type",
                    "value": "application/json"
                  },
                  {
                    "key": "Accept",
                    "value": "*/*"
                  }
                ],
                "method": "POST",
                "body": {
                  "mode": "raw",
                  "raw": "{\n  \"repoUrl\": \"https://github.com/UMSDqA/WtH9LVk9W.git\"\n}",
                  "options": {
                    "raw": {
                      "headerFamily": "json",
                      "language": "json"
                    }
                  }
                }
              },
              "status": "OK",
              "code": 200,
              "header": [
                {
                  "key": "Content-Type",
                  "value": "*/*"
                }
              ],
              "body": "{\n  \"id\": \"<long>\",\n  \"projectName\": \"<string>\",\n  \"description\": \"<string>\",\n  \"readmeContent\": \"<string>\",\n  \"techStack\": [\n    \"<string>\",\n    \"<string>\"\n  ],\n  \"detectedFeatures\": [\n    \"<string>\",\n    \"<string>\"\n  ],\n  \"createdAt\": \"<dateTime>\"\n}",
              "cookie": [],
              "_postman_previewlanguage": "text"
            },
            {
              "id": "debf4847-8050-4ddc-a018-ba6e32ff53b8",
              "name": "Invalid repository URL",
              "originalRequest": {
                "url": {
                  "path": [
                    "api",
                    "v1",
                    "repos",
                    "analyze"
                  ],
                  "host": [
                    "{{baseUrl}}"
                  ],
                  "query": [],
                  "variable": []
                },
                "header": [
                  {
                    "key": "Content-Type",
                    "value": "application/json"
                  },
                  {
                    "key": "Accept",
                    "value": "*/*"
                  }
                ],
                "method": "POST",
                "body": {
                  "mode": "raw",
                  "raw": "{\n  \"repoUrl\": \"https://github.com/UMSDqA/WtH9LVk9W.git\"\n}",
                  "options": {
                    "raw": {
                      "headerFamily": "json",
                      "language": "json"
                    }
                  }
                }
              },
              "status": "Bad Request",
              "code": 400,
              "header": [
                {
                  "key": "Content-Type",
                  "value": "*/*"
                }
              ],
              "body": "{\n  \"id\": \"<long>\",\n  \"projectName\": \"<string>\",\n  \"description\": \"<string>\",\n  \"readmeContent\": \"<string>\",\n  \"techStack\": [\n    \"<string>\",\n    \"<string>\"\n  ],\n  \"detectedFeatures\": [\n    \"<string>\",\n    \"<string>\"\n  ],\n  \"createdAt\": \"<dateTime>\"\n}",
              "cookie": [],
              "_postman_previewlanguage": "text"
            },
            {
              "id": "7b3e9b2a-46e5-492b-9bd8-b25d28be1835",
              "name": "Repository not found",
              "originalRequest": {
                "url": {
                  "path": [
                    "api",
                    "v1",
                    "repos",
                    "analyze"
                  ],
                  "host": [
                    "{{baseUrl}}"
                  ],
                  "query": [],
                  "variable": []
                },
                "header": [
                  {
                    "key": "Content-Type",
                    "value": "application/json"
                  },
                  {
                    "key": "Accept",
                    "value": "*/*"
                  }
                ],
                "method": "POST",
                "body": {
                  "mode": "raw",
                  "raw": "{\n  \"repoUrl\": \"https://github.com/UMSDqA/WtH9LVk9W.git\"\n}",
                  "options": {
                    "raw": {
                      "headerFamily": "json",
                      "language": "json"
                    }
                  }
                }
              },
              "status": "Not Found",
              "code": 404,
              "header": [
                {
                  "key": "Content-Type",
                  "value": "*/*"
                }
              ],
              "body": "{\n  \"id\": \"<long>\",\n  \"projectName\": \"<string>\",\n  \"description\": \"<string>\",\n  \"readmeContent\": \"<string>\",\n  \"techStack\": [\n    \"<string>\",\n    \"<string>\"\n  ],\n  \"detectedFeatures\": [\n    \"<string>\",\n    \"<string>\"\n  ],\n  \"createdAt\": \"<dateTime>\"\n}",
              "cookie": [],
              "_postman_previewlanguage": "text"
            }
          ],
          "event": [],
          "protocolProfileBehavior": {
            "disableBodyPruning": true
          }
        },
        {
          "id": "73dc3533-ee42-4ec2-ad12-e8e43b747adc",
          "name": "List all analyses",
          "request": {
            "name": "List all analyses",
            "description": {
              "content": "Returns all repository analyses ordered by creation date",
              "type": "text/plain"
            },
            "url": {
              "path": [
                "api",
                "v1",
                "repos",
                "analyses"
              ],
              "host": [
                "{{baseUrl}}"
              ],
              "query": [],
              "variable": []
            },
            "header": [
              {
                "key": "Accept",
                "value": "*/*"
              }
            ],
            "method": "GET",
            "body": {},
            "auth": null
          },
          "response": [
            {
              "id": "ceb9aefb-4c7b-45d4-bee0-0af676c99ff7",
              "name": "OK",
              "originalRequest": {
                "url": {
                  "path": [
                    "api",
                    "v1",
                    "repos",
                    "analyses"
                  ],
                  "host": [
                    "{{baseUrl}}"
                  ],
                  "query": [],
                  "variable": []
                },
                "header": [
                  {
                    "key": "Accept",
                    "value": "*/*"
                  }
                ],
                "method": "GET",
                "body": {}
              },
              "status": "OK",
              "code": 200,
              "header": [
                {
                  "key": "Content-Type",
                  "value": "*/*"
                }
              ],
              "body": "[\n  {\n    \"id\": \"<long>\",\n    \"projectName\": \"<string>\",\n    \"description\": \"<string>\",\n    \"readmeContent\": \"<string>\",\n    \"techStack\": [\n      \"<string>\",\n      \"<string>\"\n    ],\n    \"detectedFeatures\": [\n      \"<string>\",\n      \"<string>\"\n    ],\n    \"createdAt\": \"<dateTime>\"\n  },\n  {\n    \"id\": \"<long>\",\n    \"projectName\": \"<string>\",\n    \"description\": \"<string>\",\n    \"readmeContent\": \"<string>\",\n    \"techStack\": [\n      \"<string>\",\n      \"<string>\"\n    ],\n    \"detectedFeatures\": [\n      \"<string>\",\n      \"<string>\"\n    ],\n    \"createdAt\": \"<dateTime>\"\n  }\n]",
              "cookie": [],
              "_postman_previewlanguage": "text"
            }
          ],
          "event": [],
          "protocolProfileBehavior": {
            "disableBodyPruning": true
          }
        },
        {
          "id": "c1219cd9-aa8e-472d-a33d-dd5edd940353",
          "name": "Get analysis by ID",
          "request": {
            "name": "Get analysis by ID",
            "description": {
              "content": "Returns a specific repository analysis",
              "type": "text/plain"
            },
            "url": {
              "path": [
                "api",
                "v1",
                "repos",
                "analyses",
                ":id"
              ],
              "host": [
                "{{baseUrl}}"
              ],
              "query": [],
              "variable": [
                {
                  "type": "any",
                  "value": "<long>",
                  "key": "id",
                  "disabled": false,
                  "description": {
                    "content": "(Required) ",
                    "type": "text/plain"
                  }
                }
              ]
            },
            "header": [
              {
                "key": "Accept",
                "value": "*/*"
              }
            ],
            "method": "GET",
            "body": {},
            "auth": null
          },
          "response": [
            {
              "id": "47af32a4-b30c-4df2-b272-7bf8bc0b1dac",
              "name": "Analysis found",
              "originalRequest": {
                "url": {
                  "path": [
                    "api",
                    "v1",
                    "repos",
                    "analyses",
                    ":id"
                  ],
                  "host": [
                    "{{baseUrl}}"
                  ],
                  "query": [],
                  "variable": [
                    {
                      "disabled": false,
                      "description": {
                        "content": "(Required) ",
                        "type": "text/plain"
                      },
                      "type": "any",
                      "value": "<long>",
                      "key": "id"
                    }
                  ]
                },
                "header": [
                  {
                    "key": "Accept",
                    "value": "*/*"
                  }
                ],
                "method": "GET",
                "body": {}
              },
              "status": "OK",
              "code": 200,
              "header": [
                {
                  "key": "Content-Type",
                  "value": "*/*"
                }
              ],
              "body": "{\n  \"id\": \"<long>\",\n  \"projectName\": \"<string>\",\n  \"description\": \"<string>\",\n  \"readmeContent\": \"<string>\",\n  \"techStack\": [\n    \"<string>\",\n    \"<string>\"\n  ],\n  \"detectedFeatures\": [\n    \"<string>\",\n    \"<string>\"\n  ],\n  \"createdAt\": \"<dateTime>\"\n}",
              "cookie": [],
              "_postman_previewlanguage": "text"
            },
            {
              "id": "87000497-6d42-462d-9485-bd9dfb0d76d4",
              "name": "Analysis not found",
              "originalRequest": {
                "url": {
                  "path": [
                    "api",
                    "v1",
                    "repos",
                    "analyses",
                    ":id"
                  ],
                  "host": [
                    "{{baseUrl}}"
                  ],
                  "query": [],
                  "variable": [
                    {
                      "disabled": false,
                      "description": {
                        "content": "(Required) ",
                        "type": "text/plain"
                      },
                      "type": "any",
                      "value": "<long>",
                      "key": "id"
                    }
                  ]
                },
                "header": [
                  {
                    "key": "Accept",
                    "value": "*/*"
                  }
                ],
                "method": "GET",
                "body": {}
              },
              "status": "Not Found",
              "code": 404,
              "header": [
                {
                  "key": "Content-Type",
                  "value": "*/*"
                }
              ],
              "body": "{\n  \"id\": \"<long>\",\n  \"projectName\": \"<string>\",\n  \"description\": \"<string>\",\n  \"readmeContent\": \"<string>\",\n  \"techStack\": [\n    \"<string>\",\n    \"<string>\"\n  ],\n  \"detectedFeatures\": [\n    \"<string>\",\n    \"<string>\"\n  ],\n  \"createdAt\": \"<dateTime>\"\n}",
              "cookie": [],
              "_postman_previewlanguage": "text"
            }
          ],
          "event": [],
          "protocolProfileBehavior": {
            "disableBodyPruning": true
          }
        }
      ]
    },
    {
      "name": "home-controller",
      "description": "",
      "item": [
        {
          "id": "b37612ae-8f84-4912-a64a-5df3080a5bed",
          "name": "home",
          "request": {
            "name": "home",
            "description": {},
            "url": {
              "path": [
                ""
              ],
              "host": [
                "{{baseUrl}}"
              ],
              "query": [],
              "variable": []
            },
            "header": [
              {
                "key": "Accept",
                "value": "*/*"
              }
            ],
            "method": "GET",
            "body": {},
            "auth": null
          },
          "response": [
            {
              "id": "470f33fc-6956-4de9-a83c-eec97d025247",
              "name": "OK",
              "originalRequest": {
                "url": {
                  "path": [
                    ""
                  ],
                  "host": [
                    "{{baseUrl}}"
                  ],
                  "query": [],
                  "variable": []
                },
                "header": [
                  {
                    "key": "Accept",
                    "value": "*/*"
                  }
                ],
                "method": "GET",
                "body": {}
              },
              "status": "OK",
              "code": 200,
              "header": [
                {
                  "key": "Content-Type",
                  "value": "*/*"
                }
              ],
              "body": "<string>",
              "cookie": [],
              "_postman_previewlanguage": "text"
            }
          ],
          "event": [],
          "protocolProfileBehavior": {
            "disableBodyPruning": true
          }
        }
      ]
    }
  ],
  "event": [],
  "variable": [
    {
      "key": "baseUrl",
      "value": "https://serviceportfolioapi.pablohgdev.com"
    }
  ],
  "info": {
    "_postman_id": "209b76d1-ac1a-4e54-b020-5f894e6a0296",
    "name": "Service Portfolio API - Auto-generated",
    "schema": "https://schema.getpostman.com/json/collection/v2.1.0/collection.json",
    "description": "Collection auto-generated from OpenAPI spec.\n\nDate: 2026-02-16 20:41 UTC\nEnvironment: dev\n\nGenerated by GitHub Actions workflow."
  }
}
