{
  "item": [
    {
      "name": "Portfolio Generation",
      "description": "Generate professional developer portfolios from GitHub profiles",
      "item": [
        {
          "id": "33335116-f60b-4dd7-9459-cdc24b8bd276",
          "name": "Generate developer portfolio",
          "request": {
            "name": "Generate developer portfolio",
            "description": {
              "content": "Scans a GitHub user's public repositories and generates a professional portfolio with AI",
              "type": "text/plain"
            },
            "url": {
              "path": [
                "api",
                "v1",
                "portfolio",
                "generate"
              ],
              "host": [
                "{{baseUrl}}"
              ],
              "query": [],
              "variable": []
            },
            "header": [
              {
                "key": "Content-Type",
                "value": "application/json"
              },
              {
                "key": "Accept",
                "value": "*/*"
              }
            ],
            "method": "POST",
            "body": {
              "mode": "raw",
              "raw": "{\n  \"githubUsername\": \"<string>\"\n}",
              "options": {
                "raw": {
                  "headerFamily": "json",
                  "language": "json"
                }
              }
            },
            "auth": null
          },
          "response": [
            {
              "id": "21be46ee-0359-474f-bf7d-4b4eb711103b",
              "name": "Portfolio generated successfully",
              "originalRequest": {
                "url": {
                  "path": [
                    "api",
                    "v1",
                    "portfolio",
                    "generate"
                  ],
                  "host": [
                    "{{baseUrl}}"
                  ],
                  "query": [],
                  "variable": []
                },
                "header": [
                  {
                    "key": "Content-Type",
                    "value": "application/json"
                  },
                  {
                    "key": "Accept",
                    "value": "*/*"
                  }
                ],
                "method": "POST",
                "body": {
                  "mode": "raw",
                  "raw": "{\n  \"githubUsername\": \"<string>\"\n}",
                  "options": {
                    "raw": {
                      "headerFamily": "json",
                      "language": "json"
                    }
                  }
                }
              },
              "status": "OK",
              "code": 200,
              "header": [
                {
                  "key": "Content-Type",
                  "value": "*/*"
                }
              ],
              "body": "{\n  \"id\": \"<long>\",\n  \"githubUsername\": \"<string>\",\n  \"developerName\": \"<string>\",\n  \"professionalSummary\": \"<string>\",\n  \"topSkills\": [\n    \"<string>\",\n    \"<string>\"\n  ],\n  \"selectedProjects\": [\n    {\n      \"repoName\": \"<string>\",\n      \"repoUrl\": \"<string>\",\n      \"description\": \"<string>\",\n      \"techStack\": [\n        \"<string>\",\n        \"<string>\"\n      ],\n      \"whyNotable\": \"<string>\",\n      \"category\": \"<string>\"\n    },\n    {\n      \"repoName\": \"<string>\",\n      \"repoUrl\": \"<string>\",\n      \"description\": \"<string>\",\n      \"techStack\": [\n        \"<string>\",\n        \"<string>\"\n      ],\n      \"whyNotable\": \"<string>\",\n      \"category\": \"<string>\"\n    }\n  ],\n  \"skillsByCategory\": {\n    \"key_0\": [\n      \"<string>\",\n      \"<string>\"\n    ]\n  },\n  \"profileHighlights\": [\n    \"<string>\",\n    \"<string>\"\n  ],\n  \"totalPublicRepos\": \"<integer>\",\n  \"createdAt\": \"<dateTime>\"\n}",
              "cookie": [],
              "_postman_previewlanguage": "text"
            },
            {
              "id": "72e899d4-eab7-4e55-a82b-7276d8a6b6d0",
              "name": "Invalid GitHub username",
              "originalRequest": {
                "url": {
                  "path": [
                    "api",
                    "v1",
                    "portfolio",
                    "generate"
                  ],
                  "host": [
                    "{{baseUrl}}"
                  ],
                  "query": [],
                  "variable": []
                },
                "header": [
                  {
                    "key": "Content-Type",
                    "value": "application/json"
                  },
                  {
                    "key": "Accept",
                    "value": "*/*"
                  }
                ],
                "method": "POST",
                "body": {
                  "mode": "raw",
                  "raw": "{\n  \"githubUsername\": \"<string>\"\n}",
                  "options": {
                    "raw": {
                      "headerFamily": "json",
                      "language": "json"
                    }
                  }
                }
              },
              "status": "Bad Request",
              "code": 400,
              "header": [
                {
                  "key": "Content-Type",
                  "value": "*/*"
                }
              ],
              "body": "{\n  \"id\": \"<long>\",\n  \"githubUsername\": \"<string>\",\n  \"developerName\": \"<string>\",\n  \"professionalSummary\": \"<string>\",\n  \"topSkills\": [\n    \"<string>\",\n    \"<string>\"\n  ],\n  \"selectedProjects\": [\n    {\n      \"repoName\": \"<string>\",\n      \"repoUrl\": \"<string>\",\n      \"description\": \"<string>\",\n      \"techStack\": [\n        \"<string>\",\n        \"<string>\"\n      ],\n      \"whyNotable\": \"<string>\",\n      \"category\": \"<string>\"\n    },\n    {\n      \"repoName\": \"<string>\",\n      \"repoUrl\": \"<string>\",\n      \"description\": \"<string>\",\n      \"techStack\": [\n        \"<string>\",\n        \"<string>\"\n      ],\n      \"whyNotable\": \"<string>\",\n      \"category\": \"<string>\"\n    }\n  ],\n  \"skillsByCategory\": {\n    \"key_0\": [\n      \"<string>\",\n      \"<string>\"\n    ]\n  },\n  \"profileHighlights\": [\n    \"<string>\",\n    \"<string>\"\n  ],\n  \"totalPublicRepos\": \"<integer>\",\n  \"createdAt\": \"<dateTime>\"\n}",
              "cookie": [],
              "_postman_previewlanguage": "text"
            },
            {
              "id": "3f98b3f1-f245-4d70-9df7-788855d739a5",
              "name": "GitHub user not found",
              "originalRequest": {
                "url": {
                  "path": [
                    "api",
                    "v1",
                    "portfolio",
                    "generate"
                  ],
                  "host": [
                    "{{baseUrl}}"
                  ],
                  "query": [],
                  "variable": []
                },
                "header": [
                  {
                    "key": "Content-Type",
                    "value": "application/json"
                  },
                  {
                    "key": "Accept",
                    "value": "*/*"
                  }
                ],
                "method": "POST",
                "body": {
                  "mode": "raw",
                  "raw": "{\n  \"githubUsername\": \"<string>\"\n}",
                  "options": {
                    "raw": {
                      "headerFamily": "json",
                      "language": "json"
                    }
                  }
                }
              },
              "status": "Not Found",
              "code": 404,
              "header": [
                {
                  "key": "Content-Type",
                  "value": "*/*"
                }
              ],
              "body": "{\n  \"id\": \"<long>\",\n  \"githubUsername\": \"<string>\",\n  \"developerName\": \"<string>\",\n  \"professionalSummary\": \"<string>\",\n  \"topSkills\": [\n    \"<string>\",\n    \"<string>\"\n  ],\n  \"selectedProjects\": [\n    {\n      \"repoName\": \"<string>\",\n      \"repoUrl\": \"<string>\",\n      \"description\": \"<string>\",\n      \"techStack\": [\n        \"<string>\",\n        \"<string>\"\n      ],\n      \"whyNotable\": \"<string>\",\n      \"category\": \"<string>\"\n    },\n    {\n      \"repoName\": \"<string>\",\n      \"repoUrl\": \"<string>\",\n      \"description\": \"<string>\",\n      \"techStack\": [\n        \"<string>\",\n        \"<string>\"\n      ],\n      \"whyNotable\": \"<string>\",\n      \"category\": \"<string>\"\n    }\n  ],\n  \"skillsByCategory\": {\n    \"key_0\": [\n      \"<string>\",\n      \"<string>\"\n    ]\n  },\n  \"profileHighlights\": [\n    \"<string>\",\n    \"<string>\"\n  ],\n  \"totalPublicRepos\": \"<integer>\",\n  \"createdAt\": \"<dateTime>\"\n}",
              "cookie": [],
              "_postman_previewlanguage": "text"
            }
          ],
          "event": [],
          "protocolProfileBehavior": {
            "disableBodyPruning": true
          }
        },
        {
          "id": "d1432bab-6faa-404d-a3d4-a0982f9ce5b3",
          "name": "List all portfolios",
          "request": {
            "name": "List all portfolios",
            "description": {
              "content": "Returns summary of all generated portfolios",
              "type": "text/plain"
            },
            "url": {
              "path": [
                "api",
                "v1",
                "portfolio"
              ],
              "host": [
                "{{baseUrl}}"
              ],
              "query": [],
              "variable": []
            },
            "header": [
              {
                "key": "Accept",
                "value": "*/*"
              }
            ],
            "method": "GET",
            "body": {},
            "auth": null
          },
          "response": [
            {
              "id": "21fed621-a449-4c89-86da-f6aa2fbf077b",
              "name": "OK",
              "originalRequest": {
                "url": {
                  "path": [
                    "api",
                    "v1",
                    "portfolio"
                  ],
                  "host": [
                    "{{baseUrl}}"
                  ],
                  "query": [],
                  "variable": []
                },
                "header": [
                  {
                    "key": "Accept",
                    "value": "*/*"
                  }
                ],
                "method": "GET",
                "body": {}
              },
              "status": "OK",
              "code": 200,
              "header": [
                {
                  "key": "Content-Type",
                  "value": "*/*"
                }
              ],
              "body": "[\n  {\n    \"id\": \"<long>\",\n    \"githubUsername\": \"<string>\",\n    \"developerName\": \"<string>\",\n    \"professionalSummary\": \"<string>\",\n    \"topSkills\": [\n      \"<string>\",\n      \"<string>\"\n    ],\n    \"totalPublicRepos\": \"<integer>\",\n    \"projectCount\": \"<integer>\",\n    \"createdAt\": \"<dateTime>\"\n  },\n  {\n    \"id\": \"<long>\",\n    \"githubUsername\": \"<string>\",\n    \"developerName\": \"<string>\",\n    \"professionalSummary\": \"<string>\",\n    \"topSkills\": [\n      \"<string>\",\n      \"<string>\"\n    ],\n    \"totalPublicRepos\": \"<integer>\",\n    \"projectCount\": \"<integer>\",\n    \"createdAt\": \"<dateTime>\"\n  }\n]",
              "cookie": [],
              "_postman_previewlanguage": "text"
            }
          ],
          "event": [],
          "protocolProfileBehavior": {
            "disableBodyPruning": true
          }
        },
        {
          "id": "cb4721d0-050f-420b-9499-b65a62e27334",
          "name": "Get portfolio by ID",
          "request": {
            "name": "Get portfolio by ID",
            "description": {},
            "url": {
              "path": [
                "api",
                "v1",
                "portfolio",
                ":id"
              ],
              "host": [
                "{{baseUrl}}"
              ],
              "query": [],
              "variable": [
                {
                  "type": "any",
                  "value": "<long>",
                  "key": "id",
                  "disabled": false,
                  "description": {
                    "content": "(Required) ",
                    "type": "text/plain"
                  }
                }
              ]
            },
            "header": [
              {
                "key": "Accept",
                "value": "*/*"
              }
            ],
            "method": "GET",
            "body": {},
            "auth": null
          },
          "response": [
            {
              "id": "79bc385b-f6c9-4468-9f13-745aa6b50967",
              "name": "Portfolio found",
              "originalRequest": {
                "url": {
                  "path": [
                    "api",
                    "v1",
                    "portfolio",
                    ":id"
                  ],
                  "host": [
                    "{{baseUrl}}"
                  ],
                  "query": [],
                  "variable": [
                    {
                      "disabled": false,
                      "description": {
                        "content": "(Required) ",
                        "type": "text/plain"
                      },
                      "type": "any",
                      "value": "<long>",
                      "key": "id"
                    }
                  ]
                },
                "header": [
                  {
                    "key": "Accept",
                    "value": "*/*"
                  }
                ],
                "method": "GET",
                "body": {}
              },
              "status": "OK",
              "code": 200,
              "header": [
                {
                  "key": "Content-Type",
                  "value": "*/*"
                }
              ],
              "body": "{\n  \"id\": \"<long>\",\n  \"githubUsername\": \"<string>\",\n  \"developerName\": \"<string>\",\n  \"professionalSummary\": \"<string>\",\n  \"topSkills\": [\n    \"<string>\",\n    \"<string>\"\n  ],\n  \"selectedProjects\": [\n    {\n      \"repoName\": \"<string>\",\n      \"repoUrl\": \"<string>\",\n      \"description\": \"<string>\",\n      \"techStack\": [\n        \"<string>\",\n        \"<string>\"\n      ],\n      \"whyNotable\": \"<string>\",\n      \"category\": \"<string>\"\n    },\n    {\n      \"repoName\": \"<string>\",\n      \"repoUrl\": \"<string>\",\n      \"description\": \"<string>\",\n      \"techStack\": [\n        \"<string>\",\n        \"<string>\"\n      ],\n      \"whyNotable\": \"<string>\",\n      \"category\": \"<string>\"\n    }\n  ],\n  \"skillsByCategory\": {\n    \"key_0\": [\n      \"<string>\",\n      \"<string>\"\n    ]\n  },\n  \"profileHighlights\": [\n    \"<string>\",\n    \"<string>\"\n  ],\n  \"totalPublicRepos\": \"<integer>\",\n  \"createdAt\": \"<dateTime>\"\n}",
              "cookie": [],
              "_postman_previewlanguage": "text"
            },
            {
              "id": "a22411be-d7e7-4f29-be37-4c6ba3495cef",
              "name": "Portfolio not found",
              "originalRequest": {
                "url": {
                  "path": [
                    "api",
                    "v1",
                    "portfolio",
                    ":id"
                  ],
                  "host": [
                    "{{baseUrl}}"
                  ],
                  "query": [],
                  "variable": [
                    {
                      "disabled": false,
                      "description": {
                        "content": "(Required) ",
                        "type": "text/plain"
                      },
                      "type": "any",
                      "value": "<long>",
                      "key": "id"
                    }
                  ]
                },
                "header": [
                  {
                    "key": "Accept",
                    "value": "*/*"
                  }
                ],
                "method": "GET",
                "body": {}
              },
              "status": "Not Found",
              "code": 404,
              "header": [
                {
                  "key": "Content-Type",
                  "value": "*/*"
                }
              ],
              "body": "{\n  \"id\": \"<long>\",\n  \"githubUsername\": \"<string>\",\n  \"developerName\": \"<string>\",\n  \"professionalSummary\": \"<string>\",\n  \"topSkills\": [\n    \"<string>\",\n    \"<string>\"\n  ],\n  \"selectedProjects\": [\n    {\n      \"repoName\": \"<string>\",\n      \"repoUrl\": \"<string>\",\n      \"description\": \"<string>\",\n      \"techStack\": [\n        \"<string>\",\n        \"<string>\"\n      ],\n      \"whyNotable\": \"<string>\",\n      \"category\": \"<string>\"\n    },\n    {\n      \"repoName\": \"<string>\",\n      \"repoUrl\": \"<string>\",\n      \"description\": \"<string>\",\n      \"techStack\": [\n        \"<string>\",\n        \"<string>\"\n      ],\n      \"whyNotable\": \"<string>\",\n      \"category\": \"<string>\"\n    }\n  ],\n  \"skillsByCategory\": {\n    \"key_0\": [\n      \"<string>\",\n      \"<string>\"\n    ]\n  },\n  \"profileHighlights\": [\n    \"<string>\",\n    \"<string>\"\n  ],\n  \"totalPublicRepos\": \"<integer>\",\n  \"createdAt\": \"<dateTime>\"\n}",
              "cookie": [],
              "_postman_previewlanguage": "text"
            }
          ],
          "event": [],
          "protocolProfileBehavior": {
            "disableBodyPruning": true
          }
        }
      ]
    },
    {
      "name": "Repository Analysis",
      "description": "Analyze GitHub repositories and generate READMEs",
      "item": [
        {
          "id": "c48ed63d-1394-485c-8a19-4b820a7e5f8c",
          "name": "Commit README to repository",
          "request": {
            "name": "Commit README to repository",
            "description": {
              "content": "Commits a generated README directly to the user's GitHub repository. Requires OAuth authentication.",
              "type": "text/plain"
            },
            "url": {
              "path": [
                "api",
                "v1",
                "repos",
                "readme",
                "commit"
              ],
              "host": [
                "{{baseUrl}}"
              ],
              "query": [],
              "variable": []
            },
            "header": [
              {
                "key": "Content-Type",
                "value": "application/json"
              },
              {
                "key": "Accept",
                "value": "*/*"
              }
            ],
            "method": "POST",
            "body": {
              "mode": "raw",
              "raw": "{\n  \"readmeContent\": \"<string>\",\n  \"repoUrl\": \"https://github.com/tloBUDEb3d/gF6y5BoqwFE.git\"\n}",
              "options": {
                "raw": {
                  "headerFamily": "json",
                  "language": "json"
                }
              }
            },
            "auth": null
          },
          "response": [
            {
              "id": "6d178f53-dce0-45b8-a677-ac087bebf90b",
              "name": "README committed successfully",
              "originalRequest": {
                "url": {
                  "path": [
                    "api",
                    "v1",
                    "repos",
                    "readme",
                    "commit"
                  ],
                  "host": [
                    "{{baseUrl}}"
                  ],
                  "query": [],
                  "variable": []
                },
                "header": [
                  {
                    "key": "Content-Type",
                    "value": "application/json"
                  },
                  {
                    "key": "Accept",
                    "value": "*/*"
                  }
                ],
                "method": "POST",
                "body": {
                  "mode": "raw",
                  "raw": "{\n  \"readmeContent\": \"<string>\",\n  \"repoUrl\": \"https://github.com/tloBUDEb3d/gF6y5BoqwFE.git\"\n}",
                  "options": {
                    "raw": {
                      "headerFamily": "json",
                      "language": "json"
                    }
                  }
                }
              },
              "status": "OK",
              "code": 200,
              "header": [
                {
                  "key": "Content-Type",
                  "value": "*/*"
                }
              ],
              "body": "{\n  \"commitSha\": \"<string>\",\n  \"commitUrl\": \"<string>\"\n}",
              "cookie": [],
              "_postman_previewlanguage": "text"
            },
            {
              "id": "a826e158-9e00-4147-be43-5b35c12c6c97",
              "name": "OAuth authentication required",
              "originalRequest": {
                "url": {
                  "path": [
                    "api",
                    "v1",
                    "repos",
                    "readme",
                    "commit"
                  ],
                  "host": [
                    "{{baseUrl}}"
                  ],
                  "query": [],
                  "variable": []
                },
                "header": [
                  {
                    "key": "Content-Type",
                    "value": "application/json"
                  },
                  {
                    "key": "Accept",
                    "value": "*/*"
                  }
                ],
                "method": "POST",
                "body": {
                  "mode": "raw",
                  "raw": "{\n  \"readmeContent\": \"<string>\",\n  \"repoUrl\": \"https://github.com/tloBUDEb3d/gF6y5BoqwFE.git\"\n}",
                  "options": {
                    "raw": {
                      "headerFamily": "json",
                      "language": "json"
                    }
                  }
                }
              },
              "status": "Unauthorized",
              "code": 401,
              "header": [
                {
                  "key": "Content-Type",
                  "value": "*/*"
                }
              ],
              "body": "{\n  \"commitSha\": \"<string>\",\n  \"commitUrl\": \"<string>\"\n}",
              "cookie": [],
              "_postman_previewlanguage": "text"
            },
            {
              "id": "eb020a2d-82ff-4aee-aa0a-0a4f953f9534",
              "name": "GitHub API error during commit",
              "originalRequest": {
                "url": {
                  "path": [
                    "api",
                    "v1",
                    "repos",
                    "readme",
                    "commit"
                  ],
                  "host": [
                    "{{baseUrl}}"
                  ],
                  "query": [],
                  "variable": []
                },
                "header": [
                  {
                    "key": "Content-Type",
                    "value": "application/json"
                  },
                  {
                    "key": "Accept",
                    "value": "*/*"
                  }
                ],
                "method": "POST",
                "body": {
                  "mode": "raw",
                  "raw": "{\n  \"readmeContent\": \"<string>\",\n  \"repoUrl\": \"https://github.com/tloBUDEb3d/gF6y5BoqwFE.git\"\n}",
                  "options": {
                    "raw": {
                      "headerFamily": "json",
                      "language": "json"
                    }
                  }
                }
              },
              "status": "Bad Gateway",
              "code": 502,
              "header": [
                {
                  "key": "Content-Type",
                  "value": "*/*"
                }
              ],
              "body": "{\n  \"commitSha\": \"<string>\",\n  \"commitUrl\": \"<string>\"\n}",
              "cookie": [],
              "_postman_previewlanguage": "text"
            }
          ],
          "event": [],
          "protocolProfileBehavior": {
            "disableBodyPruning": true
          }
        },
        {
          "id": "d790ebf7-5518-404d-986c-08102bdb51f6",
          "name": "Analyze a GitHub repository",
          "request": {
            "name": "Analyze a GitHub repository",
            "description": {
              "content": "Reads a GitHub repo, analyzes the code with AI, and generates a professional README",
              "type": "text/plain"
            },
            "url": {
              "path": [
                "api",
                "v1",
                "repos",
                "analyze"
              ],
              "host": [
                "{{baseUrl}}"
              ],
              "query": [],
              "variable": []
            },
            "header": [
              {
                "key": "Content-Type",
                "value": "application/json"
              },
              {
                "key": "Accept",
                "value": "*/*"
              }
            ],
            "method": "POST",
            "body": {
              "mode": "raw",
              "raw": "{\n  \"repoUrl\": \"https://github.com/oWwy/0z4A.git\"\n}",
              "options": {
                "raw": {
                  "headerFamily": "json",
                  "language": "json"
                }
              }
            },
            "auth": null
          },
          "response": [
            {
              "id": "399aa995-4308-4790-b07c-ff3079fa700e",
              "name": "Analysis completed successfully",
              "originalRequest": {
                "url": {
                  "path": [
                    "api",
                    "v1",
                    "repos",
                    "analyze"
                  ],
                  "host": [
                    "{{baseUrl}}"
                  ],
                  "query": [],
                  "variable": []
                },
                "header": [
                  {
                    "key": "Content-Type",
                    "value": "application/json"
                  },
                  {
                    "key": "Accept",
                    "value": "*/*"
                  }
                ],
                "method": "POST",
                "body": {
                  "mode": "raw",
                  "raw": "{\n  \"repoUrl\": \"https://github.com/oWwy/0z4A.git\"\n}",
                  "options": {
                    "raw": {
                      "headerFamily": "json",
                      "language": "json"
                    }
                  }
                }
              },
              "status": "OK",
              "code": 200,
              "header": [
                {
                  "key": "Content-Type",
                  "value": "*/*"
                }
              ],
              "body": "{\n  \"id\": \"<long>\",\n  \"projectName\": \"<string>\",\n  \"description\": \"<string>\",\n  \"readmeContent\": \"<string>\",\n  \"techStack\": [\n    \"<string>\",\n    \"<string>\"\n  ],\n  \"detectedFeatures\": [\n    \"<string>\",\n    \"<string>\"\n  ],\n  \"createdAt\": \"<dateTime>\"\n}",
              "cookie": [],
              "_postman_previewlanguage": "text"
            },
            {
              "id": "08c67f6a-fc41-4b9f-a144-a4e2493814a2",
              "name": "Invalid repository URL",
              "originalRequest": {
                "url": {
                  "path": [
                    "api",
                    "v1",
                    "repos",
                    "analyze"
                  ],
                  "host": [
                    "{{baseUrl}}"
                  ],
                  "query": [],
                  "variable": []
                },
                "header": [
                  {
                    "key": "Content-Type",
                    "value": "application/json"
                  },
                  {
                    "key": "Accept",
                    "value": "*/*"
                  }
                ],
                "method": "POST",
                "body": {
                  "mode": "raw",
                  "raw": "{\n  \"repoUrl\": \"https://github.com/oWwy/0z4A.git\"\n}",
                  "options": {
                    "raw": {
                      "headerFamily": "json",
                      "language": "json"
                    }
                  }
                }
              },
              "status": "Bad Request",
              "code": 400,
              "header": [
                {
                  "key": "Content-Type",
                  "value": "*/*"
                }
              ],
              "body": "{\n  \"id\": \"<long>\",\n  \"projectName\": \"<string>\",\n  \"description\": \"<string>\",\n  \"readmeContent\": \"<string>\",\n  \"techStack\": [\n    \"<string>\",\n    \"<string>\"\n  ],\n  \"detectedFeatures\": [\n    \"<string>\",\n    \"<string>\"\n  ],\n  \"createdAt\": \"<dateTime>\"\n}",
              "cookie": [],
              "_postman_previewlanguage": "text"
            },
            {
              "id": "ba2b05a3-29fe-4899-a887-d1d46c7ee605",
              "name": "Repository not found",
              "originalRequest": {
                "url": {
                  "path": [
                    "api",
                    "v1",
                    "repos",
                    "analyze"
                  ],
                  "host": [
                    "{{baseUrl}}"
                  ],
                  "query": [],
                  "variable": []
                },
                "header": [
                  {
                    "key": "Content-Type",
                    "value": "application/json"
                  },
                  {
                    "key": "Accept",
                    "value": "*/*"
                  }
                ],
                "method": "POST",
                "body": {
                  "mode": "raw",
                  "raw": "{\n  \"repoUrl\": \"https://github.com/oWwy/0z4A.git\"\n}",
                  "options": {
                    "raw": {
                      "headerFamily": "json",
                      "language": "json"
                    }
                  }
                }
              },
              "status": "Not Found",
              "code": 404,
              "header": [
                {
                  "key": "Content-Type",
                  "value": "*/*"
                }
              ],
              "body": "{\n  \"id\": \"<long>\",\n  \"projectName\": \"<string>\",\n  \"description\": \"<string>\",\n  \"readmeContent\": \"<string>\",\n  \"techStack\": [\n    \"<string>\",\n    \"<string>\"\n  ],\n  \"detectedFeatures\": [\n    \"<string>\",\n    \"<string>\"\n  ],\n  \"createdAt\": \"<dateTime>\"\n}",
              "cookie": [],
              "_postman_previewlanguage": "text"
            }
          ],
          "event": [],
          "protocolProfileBehavior": {
            "disableBodyPruning": true
          }
        },
        {
          "id": "027dcd52-845e-48ad-bdc0-fa4a225e4ec5",
          "name": "List all analyses",
          "request": {
            "name": "List all analyses",
            "description": {
              "content": "Returns all repository analyses ordered by creation date",
              "type": "text/plain"
            },
            "url": {
              "path": [
                "api",
                "v1",
                "repos",
                "analyses"
              ],
              "host": [
                "{{baseUrl}}"
              ],
              "query": [],
              "variable": []
            },
            "header": [
              {
                "key": "Accept",
                "value": "*/*"
              }
            ],
            "method": "GET",
            "body": {},
            "auth": null
          },
          "response": [
            {
              "id": "24a685ee-40bd-44a8-bc68-d9b7759b0c63",
              "name": "OK",
              "originalRequest": {
                "url": {
                  "path": [
                    "api",
                    "v1",
                    "repos",
                    "analyses"
                  ],
                  "host": [
                    "{{baseUrl}}"
                  ],
                  "query": [],
                  "variable": []
                },
                "header": [
                  {
                    "key": "Accept",
                    "value": "*/*"
                  }
                ],
                "method": "GET",
                "body": {}
              },
              "status": "OK",
              "code": 200,
              "header": [
                {
                  "key": "Content-Type",
                  "value": "*/*"
                }
              ],
              "body": "[\n  {\n    \"id\": \"<long>\",\n    \"projectName\": \"<string>\",\n    \"description\": \"<string>\",\n    \"readmeContent\": \"<string>\",\n    \"techStack\": [\n      \"<string>\",\n      \"<string>\"\n    ],\n    \"detectedFeatures\": [\n      \"<string>\",\n      \"<string>\"\n    ],\n    \"createdAt\": \"<dateTime>\"\n  },\n  {\n    \"id\": \"<long>\",\n    \"projectName\": \"<string>\",\n    \"description\": \"<string>\",\n    \"readmeContent\": \"<string>\",\n    \"techStack\": [\n      \"<string>\",\n      \"<string>\"\n    ],\n    \"detectedFeatures\": [\n      \"<string>\",\n      \"<string>\"\n    ],\n    \"createdAt\": \"<dateTime>\"\n  }\n]",
              "cookie": [],
              "_postman_previewlanguage": "text"
            }
          ],
          "event": [],
          "protocolProfileBehavior": {
            "disableBodyPruning": true
          }
        },
        {
          "id": "9dd66870-b513-4610-9e45-ee429c6b3453",
          "name": "Get analysis by ID",
          "request": {
            "name": "Get analysis by ID",
            "description": {
              "content": "Returns a specific repository analysis",
              "type": "text/plain"
            },
            "url": {
              "path": [
                "api",
                "v1",
                "repos",
                "analyses",
                ":id"
              ],
              "host": [
                "{{baseUrl}}"
              ],
              "query": [],
              "variable": [
                {
                  "type": "any",
                  "value": "<long>",
                  "key": "id",
                  "disabled": false,
                  "description": {
                    "content": "(Required) ",
                    "type": "text/plain"
                  }
                }
              ]
            },
            "header": [
              {
                "key": "Accept",
                "value": "*/*"
              }
            ],
            "method": "GET",
            "body": {},
            "auth": null
          },
          "response": [
            {
              "id": "ad9ab738-a060-4e7e-9f25-590503edb4aa",
              "name": "Analysis found",
              "originalRequest": {
                "url": {
                  "path": [
                    "api",
                    "v1",
                    "repos",
                    "analyses",
                    ":id"
                  ],
                  "host": [
                    "{{baseUrl}}"
                  ],
                  "query": [],
                  "variable": [
                    {
                      "disabled": false,
                      "description": {
                        "content": "(Required) ",
                        "type": "text/plain"
                      },
                      "type": "any",
                      "value": "<long>",
                      "key": "id"
                    }
                  ]
                },
                "header": [
                  {
                    "key": "Accept",
                    "value": "*/*"
                  }
                ],
                "method": "GET",
                "body": {}
              },
              "status": "OK",
              "code": 200,
              "header": [
                {
                  "key": "Content-Type",
                  "value": "*/*"
                }
              ],
              "body": "{\n  \"id\": \"<long>\",\n  \"projectName\": \"<string>\",\n  \"description\": \"<string>\",\n  \"readmeContent\": \"<string>\",\n  \"techStack\": [\n    \"<string>\",\n    \"<string>\"\n  ],\n  \"detectedFeatures\": [\n    \"<string>\",\n    \"<string>\"\n  ],\n  \"createdAt\": \"<dateTime>\"\n}",
              "cookie": [],
              "_postman_previewlanguage": "text"
            },
            {
              "id": "732544f3-be93-43c8-b6b8-36fbd49a92ad",
              "name": "Analysis not found",
              "originalRequest": {
                "url": {
                  "path": [
                    "api",
                    "v1",
                    "repos",
                    "analyses",
                    ":id"
                  ],
                  "host": [
                    "{{baseUrl}}"
                  ],
                  "query": [],
                  "variable": [
                    {
                      "disabled": false,
                      "description": {
                        "content": "(Required) ",
                        "type": "text/plain"
                      },
                      "type": "any",
                      "value": "<long>",
                      "key": "id"
                    }
                  ]
                },
                "header": [
                  {
                    "key": "Accept",
                    "value": "*/*"
                  }
                ],
                "method": "GET",
                "body": {}
              },
              "status": "Not Found",
              "code": 404,
              "header": [
                {
                  "key": "Content-Type",
                  "value": "*/*"
                }
              ],
              "body": "{\n  \"id\": \"<long>\",\n  \"projectName\": \"<string>\",\n  \"description\": \"<string>\",\n  \"readmeContent\": \"<string>\",\n  \"techStack\": [\n    \"<string>\",\n    \"<string>\"\n  ],\n  \"detectedFeatures\": [\n    \"<string>\",\n    \"<string>\"\n  ],\n  \"createdAt\": \"<dateTime>\"\n}",
              "cookie": [],
              "_postman_previewlanguage": "text"
            }
          ],
          "event": [],
          "protocolProfileBehavior": {
            "disableBodyPruning": true
          }
        }
      ]
    },
    {
      "name": "home-controller",
      "description": "",
      "item": [
        {
          "id": "7264863d-f39a-40c4-aecf-a17d330b0e18",
          "name": "home",
          "request": {
            "name": "home",
            "description": {},
            "url": {
              "path": [
                ""
              ],
              "host": [
                "{{baseUrl}}"
              ],
              "query": [],
              "variable": []
            },
            "header": [
              {
                "key": "Accept",
                "value": "*/*"
              }
            ],
            "method": "GET",
            "body": {},
            "auth": null
          },
          "response": [
            {
              "id": "681219c4-3b1a-4430-8aec-a90bca39ad55",
              "name": "OK",
              "originalRequest": {
                "url": {
                  "path": [
                    ""
                  ],
                  "host": [
                    "{{baseUrl}}"
                  ],
                  "query": [],
                  "variable": []
                },
                "header": [
                  {
                    "key": "Accept",
                    "value": "*/*"
                  }
                ],
                "method": "GET",
                "body": {}
              },
              "status": "OK",
              "code": 200,
              "header": [
                {
                  "key": "Content-Type",
                  "value": "*/*"
                }
              ],
              "body": "<string>",
              "cookie": [],
              "_postman_previewlanguage": "text"
            }
          ],
          "event": [],
          "protocolProfileBehavior": {
            "disableBodyPruning": true
          }
        }
      ]
    }
  ],
  "event": [],
  "variable": [
    {
      "key": "baseUrl",
      "value": "https://serviceportfolioapi.pablohgdev.com"
    }
  ],
  "info": {
    "_postman_id": "edda0ef9-db1e-40a2-a9a5-07ac097e1b83",
    "name": "Service Portfolio API - Auto-generated",
    "schema": "https://schema.getpostman.com/json/collection/v2.1.0/collection.json",
    "description": "Collection auto-generated from OpenAPI spec.\n\nDate: 2026-02-13 17:51 UTC\nEnvironment: dev\n\nGenerated by GitHub Actions workflow."
  }
}
